<?xml version="1.0"?>
<ruleset xmlns="http://windup.jboss.org/v1/xml" id="XmlJbossEsbRules">
    <rules>
        <rule id="XmlJbossEsbRules_2fmb">
            <when>
                <xmlfile as="default" matches="/jbossesb-deployment">
                </xmlfile>
            </when>
            <perform>
                <iteration>
                    <classification title="JBoss ESB Deployment Descriptor" effort="1"/>
                </iteration>
            </perform>
        </rule>
        <rule id="XmlJbossEsbRules_4mthy">
            <when>
                <xmlfile as="default" matches="/*[local-name()='jbossesb']">
                </xmlfile>
            </when>
            <perform>
                <iteration>
                    <classification title="JBoss ESB Pipeline Configuration" effort="1"/>
                </iteration>
            </perform>
        </rule>
        <rule id="XmlJbossEsbRules_6bcvk">
            <when>
                <xmlfile as="default" matches="/*[local-name()='smooks-resource-list']">
                </xmlfile>
            </when>
            <perform>
                <iteration>
                    <classification title="Smooks Configuration" effort="1"/>
                </iteration>
            </perform>
        </rule>
    </rules>
</ruleset>
